MANIFEST.in
README.txt
setup.py
docs/HISTORY.txt
docs/LICENSES.txt
docs/licenses/BSD.txt
docs/licenses/GPL.txt
docs/licenses/PythonLicense.txt
src/path.py
src/Sprout.egg-info/PKG-INFO
src/Sprout.egg-info/SOURCES.txt
src/Sprout.egg-info/dependency_links.txt
src/Sprout.egg-info/not-zip-safe
src/Sprout.egg-info/requires.txt
src/Sprout.egg-info/top_level.txt
src/sprout/__init__.py
src/sprout/blockedrange.py
src/sprout/htmllimit.py
src/sprout/htmlsubset.py
src/sprout/picodom.py
src/sprout/tagfilter.py
src/sprout/saxext/__init__.py
src/sprout/saxext/collapser.py
src/sprout/saxext/generator.py
src/sprout/saxext/hookablehandler.py
src/sprout/saxext/html2sax.py
src/sprout/saxext/interfaces.py
src/sprout/saxext/utils.py
src/sprout/saxext/xmlexport.py
src/sprout/saxext/xmlimport.py
src/sprout/saxext/tests/__init__.py
src/sprout/saxext/tests/alpha.xml
src/sprout/saxext/tests/test_collapser.py
src/sprout/saxext/tests/test_html2sax.py
src/sprout/saxext/tests/test_stablegenerator.py
src/sprout/saxext/tests/test_xmlexport.py
src/sprout/saxext/tests/test_xmlimport.py
src/sprout/tests/__init__.py
src/sprout/tests/test_blockedrange.py
src/sprout/tests/test_htmllimit.py
src/sprout/tests/test_tagfilter.py
src/sprout/tests/htmllimit_testdata/fixed.html
src/sprout/tests/htmllimit_testdata/limit_1.html
src/sprout/tests/htmllimit_testdata/limit_10.html
src/sprout/tests/htmllimit_testdata/limit_4.html
src/sprout/tests/htmllimit_testdata/limit_5.html
src/sprout/tests/htmllimit_testdata/limit_8.html
src/sprout/tests/htmllimit_testdata/start.html