Metadata-Version: 1.0
Name: Sprout
Version: 1.1.1
Summary: Common Python library which contains reusable components, developed at Infrae.
Home-page: http://infrae.com/download/Sprout
Author: Martijn Faassen
Author-email: info@infrae.com
License: BSD, GPL and PythonLicence
Keywords: html sax parser xml
Platform: UNKNOWN
Classifier: License :: OSI Approved :: BSD License
Classifier: License :: OSI Approved :: GNU General Public License (GPL)
Classifier: Programming Language :: Python
Classifier: Topic :: Software Development :: Libraries :: Python Modules
Classifier: Topic :: Text Processing :: Markup :: HTML
Classifier: Topic :: Text Processing :: Markup :: XML
Classifier: Topic :: Utilities
